Source_Code/test_2.v
module test_2();

    integer i;

    initial begin
        #200;

        for (i = 0; i < 20; i = i + 1) begin

            // Write data = address value
            tb_memory.write(i[7:0], i[9:0]);

            // Read back
            tb_memory.read(i[9:0]);

            if (tb_memory.data_out == i[7:0]) begin
                $display("-------------------------------------");
                $display("---- ADDRESS TEST PASSED (addr=%0d) ----", i);
                $display("-------------------------------------");
            end
            else begin
                $display("---- ADDRESS TEST FAILED (addr=%0d) ----", i);
            end

        end

        #100 $finish;
    end

endmodule

Source_Code/test_1.v
module test_1();

    initial begin
        #40;

        // Write A5 at address 10
        tb_memory.write(8'hA5, 10'd10);

        // Read back
        tb_memory.read(10'd10);

        if (tb_memory.data_out == 8'hA5) begin
            $display("-------------------------------------");
            $display("-------- DATA TEST 1 PASSED ---------");
            $display("-------------------------------------");
        end
        else
            $display("-------- DATA TEST 1 FAILED ---------");

        // Overwrite with 5A
        tb_memory.write(8'h5A, 10'd10);
        tb_memory.read(10'd10);

        if (tb_memory.data_out == 8'h5A) begin
            $display("-------------------------------------");
            $display("-------- DATA TEST 2 PASSED ---------");
            $display("-------------------------------------");
        end
        else
            $display("-------- DATA TEST 2 FAILED ---------");

    end

endmodule

Source_Code/mem1024x8.v
//Given 1024x8 Synchronous RAM. Perform directed Verification. Use tasks to obtain 
//good code density. Identify bugs if any. 
//memory module 
/*
module mem1024x8(clk, rst_n, wr,data_in,address,data_out); 
    input wr,clk,rst_n; 
    input [7:0]data_in; 
    input [9:0] address; 
    output [7:0]data_out; 
        reg [7:0] mem [0:1024]; // Memory Array 1024x8 
        reg [7:0] data_out; 
        integer i; 
        wire [9:0] mem_address = {address[9:1],1'b1}; 

        always @(posedge clk or negedge rst_n) begin 
            if(!rst_n) begin 
                for(i=0;i<1024;i=i+1) 
                    mem[i]<=8'd0; 
            end 
            else if(wr) 
                mem[mem_address]<=data_in; 
            else 
                data_out<=mem[mem_address]; 
        end 
endmodule
*/

/*
    These are the error that have to be rectified from the above design  :
	1)Memory size is incorrect: reg [7:0] mem [0:1024]; creates 1025 memory 
	locations instead of 1024. It should be [0:1023].

	2)Wrong address manipulation: wire [9:0] mem_address = {address[9:1],1'b1}; forces the LSB to 1, 
	so only odd addresses are accessed and even addresses are never used.

	3)Because of the modified mem_address, the actual input address is not directly used, which breaks correct memory mapping.

	4)The declaration output [7:0] data_out; followed by reg [7:0] data_out; is redundant. It should be declared once as output reg [7:0] data_out;.

	5)data_out is not assigned during reset, which can leave it in an unknown (X) state after reset in simulation.

	6)Read and write are mutually exclusive using else if(wr) ... else ..., meaning read occurs only when wr=0. 
	There is no defined behavior for simultaneous read and write requirements.

	7)Read operation is synchronous (inside posedge block), but there is no explicit comment or 
	clarity that this is synchronous memory, which may cause misunderstanding in usage.

	8)No protection against out-of-range address access (if address > 1023 due to bug elsewhere, behavior is undefined).
*/

module mem1024x8(clk, rst_n, wr,data_in,address,data_out); 
    input clk;
    input rst_n;
    input wr;
    input [7:0] data_in;
    input [9:0] address;
    output reg [7:0] data_out;

    reg [7:0] mem [0:1023];		//Changes made here
    integer i;

    always @(posedge clk or negedge rst_n) begin
        if (!rst_n) begin
            for (i = 0; i < 1024; i = i + 1)
                mem[i] <= 8'd0;
            data_out <= 8'd0;
        end
        else begin
            if (wr)
                mem[address] <= data_in;
            else
                data_out <= mem[address];
        end
    end
endmodule

Source_Code/tb_memory.v
module tb_memory();

    reg wr, clk, rst_n;
    reg [7:0] data_in;
    reg [9:0] address;
    wire [7:0] data_out;

    parameter T = 10;

    mem1024x8 dut_memory_ins (
        .clk(clk),
        .rst_n(rst_n),
        .data_in(data_in),
        .wr(wr),
        .data_out(data_out),
        .address(address)
    );

    // Clock generation
    always #(T/2) clk = ~clk;

    initial begin
        clk = 0;
        rst_n = 0;
        wr = 0;
        data_in = 0;
        address = 0;

        #20 rst_n = 1;
    end

    initial begin
        $dumpfile("mem1024x8_dump.vcd");
        $dumpvars(0, tb_memory);
    end

    initial begin
        $monitor("%0t | rst=%b | wr=%b | addr=%d | din=%h | dout=%h",$time, rst_n, wr, address, data_in, data_out);
    end

    // Write Task
    task write;
        input [7:0] din;
        input [9:0] addr;
        begin
            @(posedge clk);
            wr = 1;
            address = addr;
            data_in = din;
            @(posedge clk);
            wr = 0;
        end
    endtask

    // Read Task
    task read;
        input [9:0] addr;
        begin
            @(posedge clk);
            wr = 0;
            address = addr;
            @(posedge clk);
        end
    endtask

    // Instantiate test cases
    test_1 t1();
    test_2 t2();

endmodule

Source_Code/mem1024x8_dump.vcd
$date
	Wed Feb 18 18:42:19 2026
$end
$version
	Icarus Verilog
$end
$timescale
	1s
$end
$scope module tb_memory $end
$var wire 8 ! data_out [7:0] $end
$var parameter 32 " T $end
$var reg 10 # address [9:0] $end
$var reg 1 $ clk $end
$var reg 8 % data_in [7:0] $end
$var reg 1 & rst_n $end
$var reg 1 ' wr $end
$scope module dut_memory_ins $end
$var wire 10 ( address [9:0] $end
$var wire 1 $ clk $end
$var wire 8 ) data_in [7:0] $end
$var wire 1 & rst_n $end
$var wire 1 ' wr $end
$var reg 8 * data_out [7:0] $end
$var integer 32 + i [31:0] $end
$upscope $end
$scope module t1 $end
$upscope $end
$scope module t2 $end
$var integer 32 , i [31:0] $end
$upscope $end
$scope task read $end
$var reg 10 - addr [9:0] $end
$upscope $end
$scope task write $end
$var reg 10 . addr [9:0] $end
$var reg 8 / din [7:0] $end
$upscope $end
$upscope $end
$enddefinitions $end
$end
$dumpall
b1010 "
$end
#0
$dumpvars
bx /
bx .
bx -
bx ,
b10000000000 +
b0 *
b0 )
b0 (
0'
0&
b0 %
0$
b0 #
b0 !
$end
#5
b10000000000 +
1$
#10
0$
#15
b10000000000 +
1$
#20
0$
1&
#25
1$
#30
0$
#35
1$
#40
0$
b1010 .
b10100101 /
#45
b10100101 %
b10100101 )
b1010 #
b1010 (
1'
1$
#50
0$
#55
b10100101 !
b10100101 *
b1010 -
0'
1$
#60
0$
#65
1$
#70
0$
#75
b1011010 /
1$
#80
0$
#85
b1011010 %
b1011010 )
1'
1$
#90
0$
#95
b1011010 !
b1011010 *
0'
1$
#100
0$
#105
1$
#110
0$
#115
1$
#120
0$
#125
1$
#130
0$
#135
1$
#140
0$
#145
1$
#150
0$
#155
1$
#160
0$
#165
1$
#170
0$
#175
1$
#180
0$
#185
1$
#190
0$
#195
1$
#200
0$
b0 .
b0 /
b0 ,
#205
b0 %
b0 )
b0 #
b0 (
1'
1$
#210
0$
#215
b0 !
b0 *
b0 -
0'
1$
#220
0$
#225
1$
#230
0$
#235
b1 .
b1 /
b1 ,
1$
#240
0$
#245
b1 %
b1 )
b1 #
b1 (
1'
1$
#250
0$
#255
b1 !
b1 *
b1 -
0'
1$
#260
0$
#265
1$
#270
0$
#275
b10 .
b10 /
b10 ,
1$
#280
0$
#285
b10 %
b10 )
b10 #
b10 (
1'
1$
#290
0$
#295
b10 !
b10 *
b10 -
0'
1$
#300
0$
#305
1$
#310
0$
#315
b11 .
b11 /
b11 ,
1$
#320
0$
#325
b11 %
b11 )
b11 #
b11 (
1'
1$
#330
0$
#335
b11 !
b11 *
b11 -
0'
1$
#340
0$
#345
1$
#350
0$
#355
b100 .
b100 /
b100 ,
1$
#360
0$
#365
b100 %
b100 )
b100 #
b100 (
1'
1$
#370
0$
#375
b100 !
b100 *
b100 -
0'
1$
#380
0$
#385
1$
#390
0$
#395
b101 .
b101 /
b101 ,
1$
#400
0$
#405
b101 %
b101 )
b101 #
b101 (
1'
1$
#410
0$
#415
b101 !
b101 *
b101 -
0'
1$
#420
0$
#425
1$
#430
0$
#435
b110 .
b110 /
b110 ,
1$
#440
0$
#445
b110 %
b110 )
b110 #
b110 (
1'
1$
#450
0$
#455
b110 !
b110 *
b110 -
0'
1$
#460
0$
#465
1$
#470
0$
#475
b111 .
b111 /
b111 ,
1$
#480
0$
#485
b111 %
b111 )
b111 #
b111 (
1'
1$
#490
0$
#495
b111 !
b111 *
b111 -
0'
1$
#500
0$
#505
1$
#510
0$
#515
b1000 .
b1000 /
b1000 ,
1$
#520
0$
#525
b1000 %
b1000 )
b1000 #
b1000 (
1'
1$
#530
0$
#535
b1000 !
b1000 *
b1000 -
0'
1$
#540
0$
#545
1$
#550
0$
#555
b1001 .
b1001 /
b1001 ,
1$
#560
0$
#565
b1001 %
b1001 )
b1001 #
b1001 (
1'
1$
#570
0$
#575
b1001 !
b1001 *
b1001 -
0'
1$
#580
0$
#585
1$
#590
0$
#595
b1010 .
b1010 /
b1010 ,
1$
#600
0$
#605
b1010 %
b1010 )
b1010 #
b1010 (
1'
1$
#610
0$
#615
b1010 !
b1010 *
b1010 -
0'
1$
#620
0$
#625
1$
#630
0$
#635
b1011 .
b1011 /
b1011 ,
1$
#640
0$
#645
b1011 %
b1011 )
b1011 #
b1011 (
1'
1$
#650
0$
#655
b1011 !
b1011 *
b1011 -
0'
1$
#660
0$
#665
1$
#670
0$
#675
b1100 .
b1100 /
b1100 ,
1$
#680
0$
#685
b1100 %
b1100 )
b1100 #
b1100 (
1'
1$
#690
0$
#695
b1100 !
b1100 *
b1100 -
0'
1$
#700
0$
#705
1$
#710
0$
#715
b1101 .
b1101 /
b1101 ,
1$
#720
0$
#725
b1101 %
b1101 )
b1101 #
b1101 (
1'
1$
#730
0$
#735
b1101 !
b1101 *
b1101 -
0'
1$
#740
0$
#745
1$
#750
0$
#755
b1110 .
b1110 /
b1110 ,
1$
#760
0$
#765
b1110 %
b1110 )
b1110 #
b1110 (
1'
1$
#770
0$
#775
b1110 !
b1110 *
b1110 -
0'
1$
#780
0$
#785
1$
#790
0$
#795
b1111 .
b1111 /
b1111 ,
1$
#800
0$
#805
b1111 %
b1111 )
b1111 #
b1111 (
1'
1$
#810
0$
#815
b1111 !
b1111 *
b1111 -
0'
1$
#820
0$
#825
1$
#830
0$
#835
b10000 .
b10000 /
b10000 ,
1$
#840
0$
#845
b10000 %
b10000 )
b10000 #
b10000 (
1'
1$
#850
0$
#855
b10000 !
b10000 *
b10000 -
0'
1$
#860
0$
#865
1$
#870
0$
#875
b10001 .
b10001 /
b10001 ,
1$
#880
0$
#885
b10001 %
b10001 )
b10001 #
b10001 (
1'
1$
#890
0$
#895
b10001 !
b10001 *
b10001 -
0'
1$
#900
0$
#905
1$
#910
0$
#915
b10010 .
b10010 /
b10010 ,
1$
#920
0$
#925
b10010 %
b10010 )
b10010 #
b10010 (
1'
1$
#930
0$
#935
b10010 !
b10010 *
b10010 -
0'
1$
#940
0$
#945
1$
#950
0$
#955
b10011 .
b10011 /
b10011 ,
1$
#960
0$
#965
b10011 %
b10011 )
b10011 #
b10011 (
1'
1$
#970
0$
#975
b10011 !
b10011 *
b10011 -
0'
1$
#980
0$
#985
1$
#990
0$
#995
b10100 ,
1$
